mlchain_client/__init__.py
mlchain_client/client.py
mlchain_client-0.1.12.dist-info/LICENSE
mlchain_client-0.1.12.dist-info/METADATA
mlchain_client-0.1.12.dist-info/WHEEL
mlchain_client-0.1.12.dist-info/top_level.txt
mlchain_client-0.1.12.dist-info/RECORD
