Metadata-Version: 2.1
Name: mlchain-client
Version: 0.1.12
Summary: A package for interacting with the Mlchain Service-API
Home-page: https://github.com/mlchain/mlchain
Author: Mlchain
Author-email: hello@mlchain.khulnasoft.com
License: MIT
Keywords: mlchain nlp ai language-processing
Classifier: Programming Language :: Python :: 3
Classifier: License :: OSI Approved :: MIT License
Classifier: Operating System :: OS Independent
Requires-Python: >=3.6
License-File: LICENSE
Requires-Dist: requests
